smartauthen/__init__.py
smartauthen/auth.py
smartauthen-0.2.4.dist-info/licenses/LICENSE
smartauthen-0.2.4.dist-info/METADATA
smartauthen-0.2.4.dist-info/WHEEL
smartauthen-0.2.4.dist-info/top_level.txt
smartauthen-0.2.4.dist-info/RECORD
