Metadata-Version: 2.4
Name: smartauthen
Version: 0.2.4
Summary: Smart, simple, lightweight, secure cross-platform authentication for any application.
Home-page: https://github.com/smartlegionlab/smartauthen/
Author: A.A. Suvorov
Author-email: smartlegiondev@gmail.com
License: BSD 3-Clause License
Project-URL: Documentation, https://github.com/smartlegionlab/smartauthen/blob/master/README.md
Project-URL: Release notes, https://github.com/smartlegionlab/smartauthen/releases
Keywords: smartlegionlab,smartauthen,authentication,auth,python auth
Classifier: Development Status :: 5 - Production/Stable
Classifier: Environment :: Console
Classifier: Intended Audience :: End Users/Desktop
Classifier: Intended Audience :: System Administrators
Classifier: License :: OSI Approved :: BSD License
Classifier: Natural Language :: English
Classifier: Operating System :: OS Independent
Classifier: Operating System :: Microsoft :: Windows
Classifier: Operating System :: POSIX :: Linux
Classifier: Programming Language :: Python :: 3 :: Only
Classifier: Topic :: Software Development :: Libraries :: Python Modules
Classifier: Topic :: Utilities
Requires-Python: >=3.6
License-File: LICENSE
Dynamic: license-file
